Workbook

Sheet Budget
A1: ABC Inc. Monthly Budget Report
A2: From January - December 2023
A4: Category | B4: Sub category | C4: January | D4: February | E4: March | F4: April | G4: May | H4: June | I4: July | J4: August | K4: September | L4: October | M4: November | N4: December
A5: Income | B5: Service Revenue | C5: 5000 | D5: 5000 | E5: 15000 | F5: 15500 | G5: 16000 | H5: 16500 | I5: 17000 | J5: 17500 | K5: 18000 | L5: 18500 | M5: 19000 | N5: 20000
B6: Miscallenous Revenue | C6: 500 | D6: 300 | E6: 2000 | F6: 2200 | G6: 2100 | H6: 2300 | I6: 2400 | J6: 2500 | K6: 2600 | L6: 2700 | M6: 2800 | N6: 3000
B7: Sales | C7: 10000 | D7: 11000 | E7: 10000 | F7: 10500 | G7: 11000 | H7: 11500 | I7: 12000 | J7: 12500 | K7: 13000 | L7: 13500 | M7: 14000 | N7: 15000
B8: Other income | C8: 200 | D8: 250 | E8: 1000 | F8: 1200 | G8: 1100 | H8: 1300 | I8: 1200 | J8: 1400 | K8: 1500 | L8: 1600 | M8: 1700 | N8: 2000
B9: Total Income | C9: =SUM(C5:C8) -> 15700 | D9: =SUM(D5:D8) -> 16550 | E9: =SUM(E5:E8) -> 28000 | F9: =SUM(F5:F8) -> 29400 | G9: =SUM(G5:G8) -> 30200 | H9: =SUM(H5:H8) -> 31600 | I9: =SUM(I5:I8) -> 32600 | J9: =SUM(J5:J8) -> 33900 | ... N9: =SUM(N5:N8) -> 40000
A10: Expenses
A11: Personnel | B11: Salaries | C11: 70000 | D11: 65000 | E11: 8000 | F11: 8200 | G11: 8200 | H11: 8500 | I11: 8500 | J11: 8800 | K11: 8800 | L11: 9000 | M11: 9500 | N11: 6500
B12: Bonuses | C12: 10000 | D12: 9000 | E12: 500 | F12: 500 | G12: 700 | H12: 700 | I12: 1000 | J12: 1000 | K12: 1200 | L12: 1200 | M12: 600 | N12: 300
A13: Office | B13: Rent | C13: 15000 | D13: 15000 | E13: 2000 | F13: 2000 | G13: 2000 | H13: 2000 | I13: 2000 | J13: 2000 | K13: 2000 | L13: 2000 | M13: 2000 | N13: 2000
B14: Utilities | C14: 4000 | D14: 5000 | E14: 400 | F14: 450 | G14: 500 | H14: 550 | I14: 600 | J14: 650 | K14: 600 | L14: 550 | M14: 500 | N14: 750
A15: Technology | B15: Software Licenses | C15: 6000 | D15: 8000 | E15: 600 | F15: 600 | G15: 650 | H15: 650 | I15: 700 | J15: 700 | K15: 750 | L15: 750 | M15: 490 | N15: 800
B16: IT Support | C16: 5000 | D16: 7000 | E16: 5000 | F16: 4500 | G16: 5000 | H16: 5000 | I16: 5100 | J16: 4900 | K16: 5500 | L16: 6500 | M16: 6400 | N16: 7000
A17: Operations | B17: Travel | C17: 8000 | D17: 6000 | E17: 800 | F17: 900 | G17: 1000 | H17: 1100 | I17: 1200 | J17: 1300 | K17: 1400 | L17: 1500 | M17: 1300 | N17: 500
B18: Training | C18: 3000 | D18: 4000 | E18: 3000 | F18: 3000 | G18: 4000 | H18: 4000 | I18: 5000 | J18: 5000 | K18: 6000 | L18: 6000 | M18: 5500 | N18: 4500
A19: Finance | B19: Depreciation | C19: 7000 | D19: 7000 | E19: 7000 | F19: 7000 | G19: 7000 | H19: 7000 | I19: 7000 | J19: 7000 | K19: 7000 | L19: 7000 | M19: 7000 | N19: 7000
B20: Bank Charges | C20: 2000 | D20: 2500 | E20: 2000 | F20: 2000 | G20: 2200 | H20: 2200 | I20: 2500 | J20: 2500 | K20: 2700 | L20: 2700 | M20: 2700 | N20: 2700
A21: Miscellaneous | B21: Other Expenses | C21: 1000 | D21: 1500 | E21: 4000 | F21: 4500 | G21: 5000 | H21: 5500 | I21: 6000 | J21: 6500 | K21: 7000 | L21: 7500 | M21: 6000 | N21: 5500
B22: Total Expenses | C22: =SUM(C11:C21) -> 131000 | D22: =SUM(D11:D21) -> 130000 | E22: =SUM(E11:E21) -> 33300 | F22: =SUM(F11:F21) -> 33650 | G22: =SUM(G11:G21) -> 36250 | H22: =SUM(H11:H21) -> 37200 | I22: =SUM(I11:I21) -> 39600 | J22: =SUM(J11:J21) -> 40350 | ... N22: =SUM(N11:N21) -> 37550

Sheet Actuals 
A1: ABC Inc, Actuals Report
A2: From January 2023- December 2023
A4: Category | B4: Sub category | C4: January | D4: February | E4: March | F4: April | G4: May | H4: June | I4: July | J4: August | K4: September | L4: October | M4: November | N4: December
A5: Income | B5: Service Revenue | C5: 14200 | D5: 14800 | E5: 15300 | F5: 15200 | G5: 16400 | H5: 16100 | I5: 17300 | J5: 17100 | K5: 18200 | L5: 18000 | M5: 19200 | N5: 20500
B6: Miscallenous Revenue | C6: 1800 | D6: 2000 | E6: 2100 | F6: 2000 | G6: 2200 | H6: 2400 | I6: 2300 | J6: 2600 | K6: 2500 | L6: 2800 | M6: 1500 | N6: 1400
B7: Sales | C7: 9500 | D7: 9800 | E7: 10200 | F7: 10300 | G7: 11200 | H7: 11000 | I7: 12300 | J7: 12200 | K7: 13400 | L7: 13200 | M7: 10000 | N7: 12000
B8: Other income | C8: 900 | D8: 1000 | E8: 1100 | F8: 1100 | G8: 1200 | H8: 1300 | I8: 1400 | J8: 1300 | K8: 1600 | L8: 1500 | M8: 1700 | N8: 1400
B9: Total Income | C9: =SUM(C5:C8) -> 26400 | D9: =SUM(D5:D8) -> 27600 | E9: =SUM(E5:E8) -> 28700 | F9: =SUM(F5:F8) -> 28600 | G9: =SUM(G5:G8) -> 31000 | H9: =SUM(H5:H8) -> 30800 | I9: =SUM(I5:I8) -> 33300 | J9: =SUM(J5:J8) -> 33200 | ... N9: =SUM(N5:N8) -> 35300
A10: Expenses
A11: Personnel | B11: Salaries | C11: 7800 | D11: 7900 | E11: 8100 | F11: 8000 | G11: 8300 | H11: 8200 | I11: 8600 | J11: 8400 | K11: 8900 | L11: 8700 | M11: 9200 | N11: 9800
B12: Bonuses | C12: 400 | D12: 500 | E12: 600 | F12: 500 | G12: 800 | H12: 700 | I12: 1100 | J12: 900 | K12: 1300 | L12: 1100 | M12: 900 | N12: 800
A13: Office | B13: Rent | C13: 2000 | D13: 2000 | E13: 2000 | F13: 2000 | G13: 2000 | H13: 2000 | I13: 2000 | J13: 2000 | K13: 2000 | L13: 2000 | M13: 2000 | N13: 2000
B14: Utilities | C14: 350 | D14: 400 | E14: 480 | F14: 500 | G14: 550 | H14: 600 | I14: 650 | J14: 700 | K14: 650 | L14: 600 | M14: 750 | N14: 550
A15: Technology | B15: Software Licenses | C15: 550 | D15: 600 | E15: 650 | F15: 600 | G15: 700 | H15: 650 | I15: 750 | J15: 700 | K15: 800 | L15: 750 | M15: 700 | N15: 850
B16: IT Support | C16: 450 | D16: 500 | E16: 550 | F16: 500 | G16: 600 | H16: 550 | I16: 650 | J16: 600 | K16: 700 | L16: 650 | M16: 600 | N16: 650
A17: Operations | B17: Travel | C17: 700 | D17: 800 | E17: 900 | F17: 1000 | G17: 1100 | H17: 1200 | I17: 1300 | J17: 1400 | K17: 1500 | L17: 1600 | M17: 1600 | N17: 1300
B18: Training | C18: 250 | D18: 300 | E18: 350 | F18: 300 | G18: 450 | H18: 400 | I18: 550 | J18: 500 | K18: 650 | L18: 600 | M18: 490 | N18: 560
A19: Finance | B19: Depreciation | C19: 700 | D19: 700 | E19: 700 | F19: 700 | G19: 700 | H19: 700 | I19: 700 | J19: 700 | K19: 700 | L19: 700 | M19: 700 | N19: 700
B20: Bank Charges | C20: 180 | D20: 200 | E20: 220 | F20: 200 | G20: 240 | H20: 230 | I20: 260 | J20: 250 | K20: 280 | L20: 270 | M20: 290 | N20: 250
A21: Miscellaneous | B21: Other Expenses | C21: 350 | D21: 400 | E21: 450 | F21: 500 | G21: 550 | H21: 600 | I21: 650 | J21: 700 | K21: 750 | L21: 800 | M21: 500 | N21: 300
B22: Total Expenses | C22: =SUM(C11:C21) -> 13730 | D22: =SUM(D11:D21) -> 14300 | E22: =SUM(E11:E21) -> 15000 | F22: =SUM(F11:F21) -> 14800 | G22: =SUM(G11:G21) -> 15990 | H22: =SUM(H11:H21) -> 15830 | I22: =SUM(I11:I21) -> 17210 | J22: =SUM(J11:J21) -> 16850 | ... N22: =SUM(N11:N21) -> 17760

Sheet Budget VS Actuals
A1: ABC Inc, Variance Report
A2: From January 2023- December 2023
A4: Category | B4: Sub category | C4: Buget | D4: Actuals | E4: Variance $ | F4: Variance %
A5: Income | B5: Service Revenue | C5: =SUM(Budget!C5:N5) -> 183000 | D5: =SUM('Actuals '!C5:N5) -> 202300 | E5: =D5-C5 -> 19300 | F5: =E5/C5 -> 0.10546448
B6: Miscallenous Revenue | C6: =SUM(Budget!C6:N6) -> 25400 | D6: =SUM('Actuals '!C6:N6) -> 25600 | E6: =D6-C6 -> 200 | F6: =E6/C6 -> 0.0078740157
B7: Sales | C7: =SUM(Budget!C7:N7) -> 144000 | D7: =SUM('Actuals '!C7:N7) -> 135100 | E7: =D7-C7 -> -8900 | F7: =E7/C7 -> -0.061805556
B8: Other income | C8: =SUM(Budget!C8:N8) -> 14450 | D8: =SUM('Actuals '!C8:N8) -> 15500 | E8: =D8-C8 -> 1050 | F8: =E8/C8 -> 0.07266436
B9: Total Income | C9: =SUM(Budget!C9:N9) -> 366850 | D9: =SUM('Actuals '!C9:N9) -> 378500 | E9: =D9-C9 -> 11650 | F9: =E9/C9 -> 0.031756849
A10: Expenses
A11: Personnel | B11: Salaries | C11: =SUM(Budget!C11:N11) -> 219000 | D11: =SUM('Actuals '!C11:N11) -> 101900 | E11: =D11-C11 -> -117100 | F11: =E11/C11 -> -0.5347032
B12: Bonuses | C12: =SUM(Budget!C12:N12) -> 26700 | D12: =SUM('Actuals '!C12:N12) -> 9600 | E12: =D12-C12 -> -17100 | F12: =E12/C12 -> -0.64044944
A13: Office | B13: Rent | C13: =SUM(Budget!C13:N13) -> 50000 | D13: =SUM('Actuals '!C13:N13) -> 24000 | E13: =D13-C13 -> -26000 | F13: =E13/C13 -> -0.52
B14: Utilities | C14: =SUM(Budget!C14:N14) -> 14550 | D14: =SUM('Actuals '!C14:N14) -> 6780 | E14: =D14-C14 -> -7770 | F14: =E14/C14 -> -0.53402062
A15: Technology | B15: Software Licenses | C15: =SUM(Budget!C15:N15) -> 20690 | D15: =SUM('Actuals '!C15:N15) -> 8300 | E15: =D15-C15 -> -12390 | F15: =E15/C15 -> -0.59884002
B16: IT Support | C16: =SUM(Budget!C16:N16) -> 66900 | D16: =SUM('Actuals '!C16:N16) -> 7000 | E16: =D16-C16 -> -59900 | F16: =E16/C16 -> -0.89536622
A17: Operations | B17: Travel | C17: =SUM(Budget!C17:N17) -> 25000 | D17: =SUM('Actuals '!C17:N17) -> 14400 | E17: =D17-C17 -> -10600 | F17: =E17/C17 -> -0.424
B18: Training | C18: =SUM(Budget!C18:N18) -> 53000 | D18: =SUM('Actuals '!C18:N18) -> 5400 | E18: =D18-C18 -> -47600 | F18: =E18/C18 -> -0.89811321
A19: Finance | B19: Depreciation | C19: =SUM(Budget!C19:N19) -> 84000 | D19: =SUM('Actuals '!C19:N19) -> 8400 | E19: =D19-C19 -> -75600 | F19: =E19/C19 -> -0.9
B20: Bank Charges | C20: =SUM(Budget!C20:N20) -> 28700 | D20: =SUM('Actuals '!C20:N20) -> 2870 | E20: =D20-C20 -> -25830 | F20: =E20/C20 -> -0.9
A21: Miscellaneous | B21: Other Expenses | C21: =SUM(Budget!C21:N21) -> 60000 | D21: =SUM('Actuals '!C21:N21) -> 6550 | E21: =D21-C21 -> -53450 | F21: =E21/C21 -> -0.89083333
B22: Total Expenses | C22: =SUM(Budget!C22:N22) -> 648540 | D22: =SUM('Actuals '!C22:N22) -> 195200 | E22: =D22-C22 -> -453340 | F22: =E22/C22 -> -0.69901625
A24: Tick Mark = Within budget
A25: Exclaimatory mark = Neutral
A26: Cross mark = Over spending

Sheet Dashboard
A1: ABC Inc, Dasboard
A2: From January 2023- December 2023
A4: Row Labels | B4: Sum of Buget | C4: Sum of Actuals | D4: Sum of Variance $ | E4: Sum of Variance %
A5: Income | B5: 183000 | C5: 202300 | D5: -19300 | E5: -0.10546448
A6: Expenses
A7: Finance | B7: 84000 | C7: 8400 | D7: 75600 | E7: 0.9
A8: Miscellaneous | B8: 60000 | C8: 6550 | D8: 53450 | E8: 0.89083333
A9: Office | B9: 50000 | C9: 24000 | D9: 26000 | E9: 0.52
A10: Operations | B10: 25000 | C10: 14400 | D10: 10600 | E10: 0.424
A11: Personnel | B11: 219000 | C11: 101900 | D11: 117100 | E11: 0.5347032
A12: Technology | B12: 20690 | C12: 8300 | D12: 12390 | E12: 0.59884002
A13: (blank) | B13: 1389090 | C13: 781550 | D13: 607540 | E13: 4.5164761
A14: Grand Total | B14: 2030780 | C14: 1147400 | D14: 883380 | E14: 8.2793881

Sheet Basic functions
A1: Employee Payroll
A3: Employee ID | B3: Name | C3: Department | D3: Role | E3: Monthly Salary
A4: E1001 | B4: Sarah Kim | C4: Finance | D4: Analyst | E4: 4500
A5: E1002 | B5: John Lee | C5: HR | D5: Manager | E5: 6000
A6: E1003 | B6: Aisha Khan | C6: IT | D6: Developer | E6: 5800
A7: E1004 | B7: Mark Jones | C7: Sales | D7: Executive | E7: 4200
A8: E1005 | B8: Emma Chen | C8: Operations | D8: Coordinator | E8: 4000
A9: E1006 | B9: David Park | C9: IT | D9: Support | E9: 3800
A10: E1007 | B10: Linda Wu | C10: Finance | D10: Controller | E10: 7000
A11: E1008 | B11: Tom Harris | C11: Sales | D11: Manager | E11: 6500
